{
    "description": "",
    "tags": [
        {
            "id": 8694899,
            "tagId": 22837,
            "name": "1_018",
            "value": null,
            "labelerLogin": "inbox@datasetninja.com",
            "createdAt": "2023-10-12T09:50:44.744Z",
            "updatedAt": "2023-10-12T09:50:44.744Z"
        }
    ],
    "size": {
        "height": 720,
        "width": 1280
    },
    "objects": [
        {
            "id": 71741394,
            "classId": 6479071,
            "description": "",
            "geometryType": "polygon",
            "labelerLogin": "inbox@datasetninja.com",
            "createdAt": "2023-10-12T09:50:44.745Z",
            "updatedAt": "2023-10-12T09:50:44.745Z",
            "tags": [],
            "classTitle": "road",
            "points": {
                "exterior": [
                    [
                        1,
                        617
                    ],
                    [
                        151,
                        512
                    ],
                    [
                        375,
                        378
                    ],
                    [
                        533,
                        303
                    ],
                    [
                        671,
                        229
                    ],
                    [
                        794,
                        183
                    ],
                    [
                        902,
                        143
                    ],
                    [
                        954,
                        124
                    ],
                    [
                        1043,
                        132
                    ],
                    [
                        1199,
                        173
                    ],
                    [
                        1279,
                        205
                    ],
                    [
                        1279,
                        719
                    ],
                    [
                        0,
                        719
                    ],
                    [
                        4,
                        625
                    ]
                ],
                "interior": []
            }
        },
        {
            "id": 71741393,
            "classId": 6479072,
            "description": "",
            "geometryType": "polygon",
            "labelerLogin": "inbox@datasetninja.com",
            "createdAt": "2023-10-12T09:50:44.744Z",
            "updatedAt": "2023-10-12T09:50:44.744Z",
            "tags": [],
            "classTitle": "footpath",
            "points": {
                "exterior": [
                    [
                        2,
                        442
                    ],
                    [
                        2,
                        612
                    ],
                    [
                        147,
                        516
                    ],
                    [
                        374,
                        382
                    ],
                    [
                        534,
                        295
                    ],
                    [
                        670,
                        229
                    ],
                    [
                        798,
                        185
                    ],
                    [
                        902,
                        142
                    ],
                    [
                        934,
                        129
                    ],
                    [
                        909,
                        122
                    ],
                    [
                        761,
                        151
                    ],
                    [
                        595,
                        185
                    ],
                    [
                        408,
                        242
                    ],
                    [
                        417,
                        302
                    ],
                    [
                        330,
                        332
                    ],
                    [
                        265,
                        316
                    ],
                    [
                        151,
                        364
                    ]
                ],
                "interior": []
            }
        }
    ]
}