{
    "description": "",
    "tags": [
        {
            "id": 8693864,
            "tagId": 22836,
            "name": "1_016",
            "value": null,
            "labelerLogin": "inbox@datasetninja.com",
            "createdAt": "2023-10-12T09:49:54.913Z",
            "updatedAt": "2023-10-12T09:49:54.913Z"
        }
    ],
    "size": {
        "height": 720,
        "width": 1280
    },
    "objects": [
        {
            "id": 71738581,
            "classId": 6479071,
            "description": "",
            "geometryType": "polygon",
            "labelerLogin": "inbox@datasetninja.com",
            "createdAt": "2023-10-12T09:49:54.914Z",
            "updatedAt": "2023-10-12T09:49:54.914Z",
            "tags": [],
            "classTitle": "road",
            "points": {
                "exterior": [
                    [
                        1,
                        436
                    ],
                    [
                        164,
                        396
                    ],
                    [
                        389,
                        320
                    ],
                    [
                        486,
                        261
                    ],
                    [
                        486,
                        151
                    ],
                    [
                        578,
                        143
                    ],
                    [
                        649,
                        126
                    ],
                    [
                        718,
                        137
                    ],
                    [
                        742,
                        131
                    ],
                    [
                        817,
                        136
                    ],
                    [
                        855,
                        138
                    ],
                    [
                        854,
                        186
                    ],
                    [
                        948,
                        233
                    ],
                    [
                        1149,
                        274
                    ],
                    [
                        1114,
                        249
                    ],
                    [
                        1126,
                        244
                    ],
                    [
                        1279,
                        306
                    ],
                    [
                        1279,
                        719
                    ],
                    [
                        984,
                        719
                    ],
                    [
                        669,
                        719
                    ],
                    [
                        365,
                        719
                    ],
                    [
                        0,
                        719
                    ]
                ],
                "interior": []
            }
        }
    ]
}