{
    "description": "",
    "tags": [
        {
            "id": 8693751,
            "tagId": 22836,
            "name": "1_016",
            "value": null,
            "labelerLogin": "inbox@datasetninja.com",
            "createdAt": "2023-10-12T09:49:49.171Z",
            "updatedAt": "2023-10-12T09:49:49.171Z"
        }
    ],
    "size": {
        "height": 720,
        "width": 1280
    },
    "objects": [
        {
            "id": 71738333,
            "classId": 6479071,
            "description": "",
            "geometryType": "polygon",
            "labelerLogin": "inbox@datasetninja.com",
            "createdAt": "2023-10-12T09:49:49.173Z",
            "updatedAt": "2023-10-12T09:49:49.173Z",
            "tags": [],
            "classTitle": "road",
            "points": {
                "exterior": [
                    [
                        1172,
                        719
                    ],
                    [
                        1091,
                        603
                    ],
                    [
                        1031,
                        512
                    ],
                    [
                        986,
                        446
                    ],
                    [
                        910,
                        380
                    ],
                    [
                        830,
                        319
                    ],
                    [
                        740,
                        260
                    ],
                    [
                        663,
                        227
                    ],
                    [
                        578,
                        199
                    ],
                    [
                        513,
                        178
                    ],
                    [
                        495,
                        167
                    ],
                    [
                        521,
                        165
                    ],
                    [
                        543,
                        166
                    ],
                    [
                        541,
                        149
                    ],
                    [
                        413,
                        135
                    ],
                    [
                        338,
                        134
                    ],
                    [
                        140,
                        130
                    ],
                    [
                        2,
                        137
                    ],
                    [
                        1,
                        719
                    ],
                    [
                        1065,
                        719
                    ]
                ],
                "interior": []
            }
        },
        {
            "id": 71738332,
            "classId": 6479072,
            "description": "",
            "geometryType": "polygon",
            "labelerLogin": "inbox@datasetninja.com",
            "createdAt": "2023-10-12T09:49:49.172Z",
            "updatedAt": "2023-10-12T09:49:49.172Z",
            "tags": [],
            "classTitle": "footpath",
            "points": {
                "exterior": [
                    [
                        1171,
                        717
                    ],
                    [
                        1060,
                        536
                    ],
                    [
                        986,
                        443
                    ],
                    [
                        892,
                        359
                    ],
                    [
                        831,
                        318
                    ],
                    [
                        740,
                        258
                    ],
                    [
                        663,
                        224
                    ],
                    [
                        576,
                        198
                    ],
                    [
                        515,
                        177
                    ],
                    [
                        495,
                        166
                    ],
                    [
                        522,
                        165
                    ],
                    [
                        544,
                        165
                    ],
                    [
                        544,
                        174
                    ],
                    [
                        607,
                        197
                    ],
                    [
                        679,
                        215
                    ],
                    [
                        744,
                        235
                    ],
                    [
                        845,
                        279
                    ],
                    [
                        923,
                        322
                    ],
                    [
                        1009,
                        370
                    ],
                    [
                        1080,
                        414
                    ],
                    [
                        1150,
                        473
                    ],
                    [
                        1223,
                        539
                    ],
                    [
                        1279,
                        592
                    ],
                    [
                        1279,
                        713
                    ]
                ],
                "interior": []
            }
        }
    ]
}