{
    "description": "",
    "tags": [
        {
            "id": 8693842,
            "tagId": 22836,
            "name": "1_016",
            "value": null,
            "labelerLogin": "inbox@datasetninja.com",
            "createdAt": "2023-10-12T09:49:53.359Z",
            "updatedAt": "2023-10-12T09:49:53.359Z"
        }
    ],
    "size": {
        "height": 720,
        "width": 1280
    },
    "objects": [
        {
            "id": 71738536,
            "classId": 6479071,
            "description": "",
            "geometryType": "polygon",
            "labelerLogin": "inbox@datasetninja.com",
            "createdAt": "2023-10-12T09:49:53.361Z",
            "updatedAt": "2023-10-12T09:49:53.361Z",
            "tags": [],
            "classTitle": "road",
            "points": {
                "exterior": [
                    [
                        171,
                        711
                    ],
                    [
                        232,
                        607
                    ],
                    [
                        285,
                        516
                    ],
                    [
                        337,
                        450
                    ],
                    [
                        420,
                        375
                    ],
                    [
                        501,
                        318
                    ],
                    [
                        539,
                        283
                    ],
                    [
                        585,
                        238
                    ],
                    [
                        574,
                        228
                    ],
                    [
                        603,
                        198
                    ],
                    [
                        614,
                        195
                    ],
                    [
                        670,
                        182
                    ],
                    [
                        699,
                        181
                    ],
                    [
                        690,
                        190
                    ],
                    [
                        694,
                        201
                    ],
                    [
                        774,
                        206
                    ],
                    [
                        841,
                        211
                    ],
                    [
                        897,
                        215
                    ],
                    [
                        1002,
                        224
                    ],
                    [
                        1116,
                        229
                    ],
                    [
                        1124,
                        271
                    ],
                    [
                        1083,
                        279
                    ],
                    [
                        1134,
                        316
                    ],
                    [
                        1208,
                        356
                    ],
                    [
                        1279,
                        388
                    ],
                    [
                        1279,
                        516
                    ],
                    [
                        1278,
                        719
                    ],
                    [
                        1035,
                        718
                    ],
                    [
                        798,
                        719
                    ],
                    [
                        595,
                        718
                    ],
                    [
                        380,
                        719
                    ],
                    [
                        167,
                        719
                    ]
                ],
                "interior": []
            }
        },
        {
            "id": 71738535,
            "classId": 6479071,
            "description": "",
            "geometryType": "polygon",
            "labelerLogin": "inbox@datasetninja.com",
            "createdAt": "2023-10-12T09:49:53.361Z",
            "updatedAt": "2023-10-12T09:49:53.361Z",
            "tags": [],
            "classTitle": "road",
            "points": {
                "exterior": [
                    [
                        1276,
                        250
                    ],
                    [
                        1185,
                        234
                    ],
                    [
                        1194,
                        286
                    ],
                    [
                        1277,
                        305
                    ]
                ],
                "interior": []
            }
        },
        {
            "id": 71738534,
            "classId": 6479072,
            "description": "",
            "geometryType": "polygon",
            "labelerLogin": "inbox@datasetninja.com",
            "createdAt": "2023-10-12T09:49:53.360Z",
            "updatedAt": "2023-10-12T09:49:53.360Z",
            "tags": [],
            "classTitle": "footpath",
            "points": {
                "exterior": [
                    [
                        3,
                        715
                    ],
                    [
                        161,
                        719
                    ],
                    [
                        225,
                        609
                    ],
                    [
                        278,
                        518
                    ],
                    [
                        363,
                        416
                    ],
                    [
                        459,
                        333
                    ],
                    [
                        524,
                        290
                    ],
                    [
                        569,
                        248
                    ],
                    [
                        575,
                        238
                    ],
                    [
                        569,
                        223
                    ],
                    [
                        574,
                        199
                    ],
                    [
                        456,
                        232
                    ],
                    [
                        319,
                        293
                    ],
                    [
                        164,
                        408
                    ],
                    [
                        35,
                        549
                    ],
                    [
                        0,
                        668
                    ]
                ],
                "interior": []
            }
        },
        {
            "id": 71738533,
            "classId": 6479072,
            "description": "",
            "geometryType": "polygon",
            "labelerLogin": "inbox@datasetninja.com",
            "createdAt": "2023-10-12T09:49:53.359Z",
            "updatedAt": "2023-10-12T09:49:53.359Z",
            "tags": [],
            "classTitle": "footpath",
            "points": {
                "exterior": [
                    [
                        1275,
                        316
                    ],
                    [
                        1194,
                        290
                    ],
                    [
                        1127,
                        280
                    ],
                    [
                        1094,
                        282
                    ],
                    [
                        1138,
                        314
                    ],
                    [
                        1215,
                        352
                    ],
                    [
                        1279,
                        377
                    ]
                ],
                "interior": []
            }
        }
    ]
}